cf_json_logger/__init__.py
cf_json_logger/cf_json_formatter.py
cf_json_logger/logger.py
cf_json_logger-0.1.0.dist-info/LICENSE
cf_json_logger-0.1.0.dist-info/WHEEL
cf_json_logger-0.1.0.dist-info/METADATA
cf_json_logger-0.1.0.dist-info/RECORD
