Metadata-Version: 2.1
Name: cf-json-logger
Version: 0.1.0
Summary: Consistent web logs by Carnall Farrar Ltd.
License: MIT
Author: Leo Edwards
Author-email: leo.edwards@carnallfarrar.com
Requires-Python: >=3.9,<4.0
Classifier: License :: OSI Approved :: MIT License
Classifier: Programming Language :: Python :: 3
Classifier: Programming Language :: Python :: 3.10
Classifier: Programming Language :: Python :: 3.9
Requires-Dist: python-json-logger (>=2.0.2,<3.0.0)
